gitdatabase/client.py
gitdatabase/collection.py
gitdatabase/cursor.py
GitDatabase-0.0.5.dist-info/METADATA
GitDatabase-0.0.5.dist-info/WHEEL
GitDatabase-0.0.5.dist-info/top_level.txt
GitDatabase-0.0.5.dist-info/RECORD
