Metadata-Version: 2.1
Name: GitDatabase
Version: 0.0.5
Summary: use git repository as database
Home-page: https://github.com/mirrorhanyu/GitDatabase
Author: Han
Author-email: mirrorhanyu@gmail.com
Maintainer: Han
Maintainer-email: mirrorhanyu@gmail.com
License: UNKNOWN
Platform: UNKNOWN
Classifier: Programming Language :: Python :: 3
Classifier: Operating System :: OS Independent
Requires-Python: >=3.6
Requires-Dist: gitpython (==3.1.20)
